README.md
setup.py
pressurize/AWSManager.py
pressurize/Controller.py
pressurize/ResourceManager.py
pressurize/__init__.py
pressurize/cli.py
pressurize.egg-info/PKG-INFO
pressurize.egg-info/SOURCES.txt
pressurize.egg-info/dependency_links.txt
pressurize.egg-info/entry_points.txt
pressurize.egg-info/not-zip-safe
pressurize.egg-info/requires.txt
pressurize.egg-info/top_level.txt
pressurize/model/__init__.py
pressurize/model/model.py
pressurize/model/model_server.py
pressurize/model/model_server_utils.py
pressurize/model/deploy_template/__init__.py
pressurize/model/deploy_template/server.py