Metadata-Version: 1.1
Name: pressurize
Version: 0.27
Summary: Cloud Machine Learning Deployment
Home-page: https://github.com/mmcdermo/pressurize
Author: Morgan McDermott
Author-email: morganmcdermott@gmail.com
License: All rights reserved
Platform: UNKNOWN
Classifier: Development Status :: 2 - Pre-Alpha
Classifier: Intended Audience :: Developers
Classifier: Natural Language :: English
Classifier: Programming Language :: Python :: 2.7
